yui/__init__.py
yui/archive.py
yui/create.py
yui/drop.py
yui/git.py
yui/lastid.py
yui/list.py
yui/list_archives.py
yui/main.py
yui/open.py
yui/pick.py
yui/reset.py
yui/scope.py
yui/tsklib.py
yui-1.0.8.dist-info/LICENSE
yui-1.0.8.dist-info/METADATA
yui-1.0.8.dist-info/WHEEL
yui-1.0.8.dist-info/entry_points.txt
yui-1.0.8.dist-info/top_level.txt
yui-1.0.8.dist-info/RECORD
