Metadata-Version: 2.1
Name: yui
Version: 1.0.8
Summary: Yui: git based personal task manager
Author-email: Agavestorm Inc <somehownottaken@gmail.com>
Project-URL: Homepage, https://yuistaskmanager.github.io/
Project-URL: Bug Tracker, https://github.com/agavestorm/yui/issues
Classifier: Programming Language :: Python :: 3
Classifier: License :: OSI Approved :: MIT License
Classifier: Operating System :: OS Independent
Requires-Python: >=3.7
License-File: LICENSE
Requires-Dist: appdata (>=2)
Requires-Dist: sanitize-filename (>=1.2)
Requires-Dist: pyyaml
Requires-Dist: unidecode
